<?xml version="1.0" encoding="UTF-8"?>
<objects serializationModel="Studio.01.10.00">
    <object class="ParameterPreset" id="{46964f9e-7199-4e16-bfad-1912df6c854c}">
        <property name="name">
            <value>Stone</value>
        </property>
        <relationship name="folder">
            <destination>{030b007a-37f7-4ef6-9c64-a0dde956f70c}</destination>
        </relationship>
        <relationship name="parameter">
            <destination>{c943967f-76e1-48d9-9f1e-69379410fdce}</destination>
        </relationship>
    </object>
    <object class="GameParameter" id="{c943967f-76e1-48d9-9f1e-69379410fdce}">
        <property name="initialValue">
            <value>0</value>
        </property>
    </object>
</objects>
